winautostart
